x402_solana/__init__.py
x402_solana/agent.py
x402_solana/ai_tools.py
x402_solana/client.py
x402_solana/client_cdp.py
x402_solana/identity.py
x402_solana/infrastructure.py
x402_solana/marketplace.py
x402_solana/mcp.py
x402_solana/server.py
x402_solana/types.py
x402_solana/wallet.py
x402_solana/examples/agent_marketplace.py
x402_solana/examples/api_monetization.py
x402_solana/examples/mcpserver.py
x402_solana/tests/conftest.py
x402_solana/tests/test_agent.py
x402_solana/tests/test_client.py
x402_solana/tests/test_server.py
x402_solana/tests/test_types.py
x402_solana-2.0.1.dist-info/LICENSE
x402_solana-2.0.1.dist-info/METADATA
x402_solana-2.0.1.dist-info/WHEEL
x402_solana-2.0.1.dist-info/top_level.txt
x402_solana-2.0.1.dist-info/RECORD
