Metadata-Version: 2.1
Name: x402-solana
Version: 2.0.1
Summary: Complete x402 Protocol Implementation for Solana
Home-page: https://github.com/mega123-art/x402-solana
Author: mega123-art
License: MIT
Project-URL: Homepage, https://github.com/mega123-art/x402-solana
Project-URL: Documentation, https://x402-solana.readthedocs.io
Project-URL: Source, https://github.com/mega123-art/x402-solana
Keywords: solana,x402,crypto,payment,agent,ai,marketplace
Classifier: Programming Language :: Python :: 3
Classifier: License :: OSI Approved :: MIT License
Classifier: Operating System :: OS Independent
Classifier: Intended Audience :: Developers
Classifier: Topic :: Software Development :: Libraries :: Python Modules
Classifier: Framework :: AsyncIO
Requires-Python: >=3.8
License-File: LICENSE
Requires-Dist: solana >=0.30.0
Requires-Dist: solders >=0.18.0
Requires-Dist: httpx >=0.24.0
Requires-Dist: spl-token >=0.2.0
Requires-Dist: base58 >=2.1.1
Provides-Extra: cdp
Requires-Dist: x402 >=1.0.0 ; extra == 'cdp'
Provides-Extra: dev
Requires-Dist: pytest ; extra == 'dev'
Requires-Dist: pytest-asyncio ; extra == 'dev'
Requires-Dist: black ; extra == 'dev'
Requires-Dist: mypy ; extra == 'dev'
Provides-Extra: infrastructure
Requires-Dist: aioredis >=2.0.0 ; extra == 'infrastructure'
